instructlab/sdg/__init__.py
instructlab/sdg/_version.py
instructlab/sdg/checkpointing.py
instructlab/sdg/datamixing.py
instructlab/sdg/eval_data.py
instructlab/sdg/generate_data.py
instructlab/sdg/pipeline.py
instructlab/sdg/prompts.py
instructlab/sdg/py.typed
instructlab/sdg/registry.py
instructlab/sdg/subset_select.py
instructlab/sdg/subset_selection.py
instructlab/sdg/blocks/__init__.py
instructlab/sdg/blocks/block.py
instructlab/sdg/blocks/filterblock.py
instructlab/sdg/blocks/iterblock.py
instructlab/sdg/blocks/llmblock.py
instructlab/sdg/blocks/utilblocks.py
instructlab/sdg/cli/run_pipeline.py
instructlab/sdg/configs/__init__.py
instructlab/sdg/configs/knowledge/__init__.py
instructlab/sdg/configs/knowledge/atomic_facts.yaml
instructlab/sdg/configs/knowledge/detailed_summary.yaml
instructlab/sdg/configs/knowledge/evaluate_faithfulness.yaml
instructlab/sdg/configs/knowledge/evaluate_question.yaml
instructlab/sdg/configs/knowledge/evaluate_relevancy.yaml
instructlab/sdg/configs/knowledge/extractive_summary.yaml
instructlab/sdg/configs/knowledge/generate_questions_responses.yaml
instructlab/sdg/configs/knowledge/mcq_generation.yaml
instructlab/sdg/configs/knowledge/simple_generate_qa.yaml
instructlab/sdg/configs/knowledge/spellcheck.yaml
instructlab/sdg/configs/skills/__init__.py
instructlab/sdg/configs/skills/contexts.yaml
instructlab/sdg/configs/skills/evaluate_freeform_pair.yaml
instructlab/sdg/configs/skills/evaluate_freeform_questions.yaml
instructlab/sdg/configs/skills/evaluate_grounded_pair.yaml
instructlab/sdg/configs/skills/evaluate_grounded_questions.yaml
instructlab/sdg/configs/skills/freeform_questions.yaml
instructlab/sdg/configs/skills/freeform_responses.yaml
instructlab/sdg/configs/skills/grounded_questions.yaml
instructlab/sdg/configs/skills/grounded_responses.yaml
instructlab/sdg/configs/skills/simple_generate_qa_freeform.yaml
instructlab/sdg/configs/skills/simple_generate_qa_grounded.yaml
instructlab/sdg/encoders/__init__.py
instructlab_sdg-0.8.3.dist-info/licenses/LICENSE
instructlab_sdg-0.8.3.dist-info/METADATA
instructlab_sdg-0.8.3.dist-info/WHEEL
instructlab_sdg-0.8.3.dist-info/top_level.txt
instructlab_sdg-0.8.3.dist-info/RECORD
