Metadata-Version: 2.4
Name: instructlab-sdg
Version: 0.8.3
Summary: Synthetic Data Generation
Author-email: InstructLab <dev@instructlab.ai>
License: Apache-2.0
Project-URL: homepage, https://instructlab.ai
Project-URL: source, https://github.com/instructlab/sdg
Project-URL: issues, https://github.com/instructlab/sdg/issues
Classifier: Development Status :: 3 - Alpha
Classifier: Environment :: Console
Classifier: License :: OSI Approved :: Apache Software License
Classifier: License :: OSI Approved :: MIT License
Classifier: Operating System :: MacOS :: MacOS X
Classifier: Operating System :: POSIX :: Linux
Classifier: Topic :: Scientific/Engineering :: Artificial Intelligence
Classifier: Programming Language :: Python :: 3
Classifier: Programming Language :: Python :: 3.10
Classifier: Programming Language :: Python :: 3.11
Classifier: Programming Language :: Python :: 3.12
Classifier: Programming Language :: Python :: Implementation :: CPython
Requires-Python: >=3.10
License-File: LICENSE
Requires-Dist: click<9.0.0,>=8.1.7
Requires-Dist: datasets>=2.18.0
Requires-Dist: docling-core[chunking]>=2.25.0
Requires-Dist: docling[tesserocr]>=2.28.4; sys_platform != "darwin"
Requires-Dist: docling>=2.28.4; sys_platform == "darwin"
Requires-Dist: GitPython<4.0.0,>=3.1.42
Requires-Dist: gguf>=0.6.0
Requires-Dist: h5py>=3.12.1
Requires-Dist: httpx<1.0.0,>=0.25.0
Requires-Dist: instructlab-schema>=0.4.0
Requires-Dist: jinja2>=3.0.0
Requires-Dist: langchain-text-splitters
Requires-Dist: openai<2.0.0,>=1.13.3
Requires-Dist: numba
Requires-Dist: sentencepiece>=0.2.0
Requires-Dist: submodlib-py
Requires-Dist: tabulate>=0.9.0
Requires-Dist: tenacity!=8.4.0,>=8.3.0
Requires-Dist: transformers>=4.41.2
Requires-Dist: xdg-base-dirs>=6.0.1
Dynamic: license-file
